duf/__init__.py
duf/__main__.py
duf/conftest.py
duf/cli/__init__.py
duf/cli/api.py
duf/cli/auth.py
duf/cli/cons.py
duf/cli/deploy.py
duf/cli/host.py
duf/cli/init.py
duf/cli/log.py
duf/cli/on_host_deploy.py
duf/cli/utils.py
duf/server/__init__.py
duf/server/__main__.py
duf/server/app.py
duf/server/app_test.py
duf/server/env.py
duf-0.0.14.dist-info/METADATA
duf-0.0.14.dist-info/WHEEL
duf-0.0.14.dist-info/top_level.txt
duf-0.0.14.dist-info/RECORD
